kamaqi/__init__.py
kamaqi/__main__.py
kamaqi/add/add.py
kamaqi/config/database.py
kamaqi/config/project.py
kamaqi/main.py
kamaqi/migrate/migrate.py
kamaqi/remove/remove.py
kamaqi/run/run.py
kamaqi/show/show.py
kamaqi/start/start.py
kamaqi/templates/app/app_crud.py
kamaqi/templates/app/app_router.py
kamaqi/templates/app/app_schemas.py
kamaqi/templates/database/database.py
kamaqi/templates/database/model.py
kamaqi/templates/database/models.py
kamaqi/templates/docker/docker_compose.py
kamaqi/templates/docker/docker_file.py
kamaqi/templates/get_templates.py
kamaqi/templates/migrations/migrations_env.py
kamaqi/templates/migrations/migrations_ini.py
kamaqi/templates/migrations/migrations_script_py_mako.py
kamaqi/templates/project/project_auth.py
kamaqi/templates/project/project_env.py
kamaqi/templates/project/project_exceptions.py
kamaqi/templates/project/project_gitignore.py
kamaqi/templates/project/project_main.py
kamaqi/templates/project/project_requirements.py
kamaqi/templates/project/project_router.py
kamaqi/templates/project/project_schemas.py
kamaqi/templates/project/project_settings.py
kamaqi/upgrade/upgrade.py
kamaqi/utils/files.py
kamaqi-0.3.0.dist-info/LICENSE
kamaqi-0.3.0.dist-info/METADATA
kamaqi-0.3.0.dist-info/WHEEL
kamaqi-0.3.0.dist-info/entry_points.txt
kamaqi-0.3.0.dist-info/RECORD
