Metadata-Version: 2.1
Name: kamaqi
Version: 0.3.0
Summary: A command line app for creating Backends with FastAPI
License: MIT
Author: Mitchell Mirano
Author-email: mitchellmirano25@gmail.com
Requires-Python: >=3.10,<4.0
Classifier: License :: OSI Approved :: MIT License
Classifier: Programming Language :: Python :: 3
Classifier: Programming Language :: Python :: 3.10
Classifier: Programming Language :: Python :: 3.11
Classifier: Programming Language :: Python :: 3.12
Requires-Dist: Jinja2 (>=3.1.2,<4.0.0)
Requires-Dist: typer[all] (>=0.7.0,<0.8.0)
